<annotation>
	<folder>AVCNightHamza</folder>
	<filename>vlc-record-2021-05-03-23h45m13s-rtsp___192.168.21.45_554- 0750.jpg</filename>
	<path>E:\Python\LabelImg\AVCNightHamza\vlc-record-2021-05-03-23h45m13s-rtsp___192.168.21.45_554- 0750.jpg</path>
	<source>
		<database>Unknown</database>
	</source>
	<size>
		<width>1280</width>
		<height>720</height>
		<depth>3</depth>
	</size>
	<segmented>0</segmented>
	<object>
		<name>F1</name>
		<pose>Unspecified</pose>
		<truncated>0</truncated>
		<difficult>0</difficult>
		<bndbox>
			<xmin>598</xmin>
			<ymin>237</ymin>
			<xmax>764</xmax>
			<ymax>439</ymax>
		</bndbox>
	</object>
</annotation>
